pycounts_olliegullery/__init__.py
pycounts_olliegullery/plotting_olliegullery.py
pycounts_olliegullery/pycounts_olliegullery.py
pycounts_olliegullery-0.1.0.dist-info/LICENSE
pycounts_olliegullery-0.1.0.dist-info/METADATA
pycounts_olliegullery-0.1.0.dist-info/WHEEL
pycounts_olliegullery-0.1.0.dist-info/RECORD
